elftools/__init__.py
elftools/common/__init__.py
elftools/common/construct_utils.py
elftools/common/exceptions.py
elftools/common/py3compat.py
elftools/common/utils.py
elftools/construct/__init__.py
elftools/construct/adapters.py
elftools/construct/core.py
elftools/construct/debug.py
elftools/construct/macros.py
elftools/construct/lib/__init__.py
elftools/construct/lib/binary.py
elftools/construct/lib/bitstream.py
elftools/construct/lib/container.py
elftools/construct/lib/hex.py
elftools/construct/lib/py3compat.py
elftools/dwarf/__init__.py
elftools/dwarf/abbrevtable.py
elftools/dwarf/aranges.py
elftools/dwarf/callframe.py
elftools/dwarf/compileunit.py
elftools/dwarf/constants.py
elftools/dwarf/datatype_cpp.py
elftools/dwarf/descriptions.py
elftools/dwarf/die.py
elftools/dwarf/dwarf_expr.py
elftools/dwarf/dwarf_util.py
elftools/dwarf/dwarfinfo.py
elftools/dwarf/enums.py
elftools/dwarf/lineprogram.py
elftools/dwarf/locationlists.py
elftools/dwarf/namelut.py
elftools/dwarf/ranges.py
elftools/dwarf/structs.py
elftools/ehabi/__init__.py
elftools/ehabi/constants.py
elftools/ehabi/decoder.py
elftools/ehabi/ehabiinfo.py
elftools/ehabi/structs.py
elftools/elf/__init__.py
elftools/elf/constants.py
elftools/elf/descriptions.py
elftools/elf/dynamic.py
elftools/elf/elffile.py
elftools/elf/enums.py
elftools/elf/gnuversions.py
elftools/elf/hash.py
elftools/elf/notes.py
elftools/elf/relocation.py
elftools/elf/sections.py
elftools/elf/segments.py
elftools/elf/structs.py
pyelftools-0.29.data/scripts/readelf.py
pyelftools-0.29.dist-info/LICENSE
pyelftools-0.29.dist-info/METADATA
pyelftools-0.29.dist-info/WHEEL
pyelftools-0.29.dist-info/top_level.txt
pyelftools-0.29.dist-info/RECORD
