Metadata-Version: 1.2
Name: pyelftools
Version: 0.29
Summary: Library for analyzing ELF files and DWARF debugging information
Home-page: https://github.com/eliben/pyelftools
Author: Eli Bendersky
Author-email: eliben@gmail.com
Maintainer: Eli Bendersky
License: Public domain
Platform: Cross Platform
Classifier: Programming Language :: Python :: 2
Classifier: Programming Language :: Python :: 3
